damvitool
