Metadata-Version: 1.1
Name: damvitool
Version: 0.2.0
Summary: Sandman inspired database and schema agnostic automatic REST API creator and data viewer/analyser
Home-page: http://damvitool.readthedocs.org
Author: alex-smirnov
Author-email: smirnov.fl@yandex.ru
License: LGPL
Platform: UNKNOWN
Classifier: Programming Language :: Python
Classifier: Programming Language :: Python :: 2
Classifier: Programming Language :: Python :: 3
Classifier: Development Status :: 4 - Beta
Classifier: Natural Language :: English
Classifier: Environment :: Web Environment
Classifier: Intended Audience :: Developers
Classifier: License :: OSI Approved :: GNU Library or Lesser General Public License (LGPL)
Classifier: Operating System :: OS Independent
Classifier: Topic :: Software Development :: Libraries :: Python Modules
Classifier: Topic :: Software Development :: Libraries :: Application Frameworks
Classifier: Topic :: Internet :: WWW/HTTP :: Dynamic Content
